allisbns/__init__.py
allisbns/dataset.py
allisbns/errors.py
allisbns/isbn.py
allisbns/merge.py
allisbns/plotting.py
allisbns/ranges.py
allisbns/rearrange.py
allisbns-0.1.4.dist-info/WHEEL
allisbns-0.1.4.dist-info/METADATA
allisbns-0.1.4.dist-info/RECORD
