Metadata-Version: 2.3
Name: allisbns
Version: 0.1.4
Summary: Works with Anna's Archive's ISBN code files
Keywords: annas-archive
Author: Maxim Stolyarchuk
Author-email: Maxim Stolyarchuk <maxim.stolyarchuk@gmail.com>
License: Creative Commons Legal Code
Classifier: Development Status :: 3 - Alpha
Classifier: License :: CC0 1.0 Universal (CC0 1.0) Public Domain Dedication
Classifier: Programming Language :: Python
Classifier: Programming Language :: Python :: 3.12
Requires-Dist: bencode-py>=4.0.0
Requires-Dist: numpy>=2.3.5
Requires-Dist: zstandard>=0.25.0
Requires-Dist: sphinx>=9.0.4 ; extra == 'docs'
Requires-Dist: sphinx-mdinclude>=0.6.2 ; extra == 'docs'
Requires-Dist: allisbns[plotting] ; extra == 'examples'
Requires-Dist: jupyter>=1.1.1 ; extra == 'examples'
Requires-Dist: tqdm>=4.67.1 ; extra == 'examples'
Requires-Dist: matplotlib>=3.10.7 ; extra == 'plotting'
Requires-Python: >=3.12
Project-URL: Changelog, https://github.com/xymaxim/allisbns/blob/main/CHANGELOG.md
Project-URL: Documentation, https://allisbns.readthedocs.io/en/stable
Project-URL: GitHub, https://github.com/xymaxim/allisbns
Provides-Extra: docs
Provides-Extra: examples
Provides-Extra: plotting
